setup.cfg
setup.py
timecop/__init__.py
timecop.egg-info/PKG-INFO
timecop.egg-info/SOURCES.txt
timecop.egg-info/dependency_links.txt
timecop.egg-info/entry_points.txt
timecop.egg-info/top_level.txt
timecop.egg-info/zip-safe
timecop/tests/__init__.py
timecop/tests/test_freeze.py